chucklepy/__init__.py
chucklepy/example.py
chucklepy/fun.py
tests/test_fun.py
chucklepy-0.1.1.dist-info/LICENSE
chucklepy-0.1.1.dist-info/METADATA
chucklepy-0.1.1.dist-info/WHEEL
chucklepy-0.1.1.dist-info/top_level.txt
chucklepy-0.1.1.dist-info/RECORD
