Metadata-Version: 2.2
Name: chucklepy
Version: 0.1.1
Summary: A lighthearted Python package that brings joy.
Author-email: Xiaowei Ma <xm2212@nyu.edu>, Weite Li <wl2811@nyu.edu>, Mandy Mao <mm13721@nyu.edu>, Rishi Rana <rr4211@nyu.edu>
License: MIT
Project-URL: Homepage, https://github.com/software-students-spring2025/3-python-package-httprequest
Keywords: fun,comedy,puns,insults,lighthearted
Classifier: Programming Language :: Python :: 3
Classifier: License :: OSI Approved :: MIT License
Classifier: Operating System :: OS Independent
License-File: LICENSE
